moha/__init__.py
moha/hf/__init__.py
moha/hf/auxiliary.py
moha/hf/hf_wavefunction.py
moha/hf/scf.py
moha/hf/scf_diis.py
moha/hf/tmp.py
moha/io/__init__.py
moha/io/iobasis.py
moha/io/iofcidump.py
moha/io/iogeometry.py
moha/io/iomolden.py
moha/io/iosystem.py
moha/io/log.py
moha/io/basis_database/3-21++g(d).nwchem
moha/io/basis_database/3-21g(d).nwchem
moha/io/basis_database/3-21g.nwchem
moha/io/basis_database/4-31g.nwchem
"moha/io/basis_database/6-31++g(d,p).nwchem"
moha/io/basis_database/6-31+g(d).nwchem
"moha/io/basis_database/6-31+g(d,p).nwchem"
moha/io/basis_database/6-31+g.nwchem
moha/io/basis_database/6-31g(d).nwchem
"moha/io/basis_database/6-31g(d,p).nwchem"
moha/io/basis_database/6-31g.nwchem
moha/io/basis_database/ano-rcc.nwchem
moha/io/basis_database/aug-cc-pcvdz.nwchem
moha/io/basis_database/aug-cc-pcvqz.nwchem
moha/io/basis_database/aug-cc-pcvtz.nwchem
moha/io/basis_database/aug-cc-pv5z.nwchem
moha/io/basis_database/aug-cc-pv6z.nwchem
moha/io/basis_database/aug-cc-pvdz.nwchem
moha/io/basis_database/aug-cc-pvqz.nwchem
moha/io/basis_database/aug-cc-pvtz.nwchem
moha/io/basis_database/cc-pcvdz.nwchem
moha/io/basis_database/cc-pcvqz.nwchem
moha/io/basis_database/cc-pcvtz.nwchem
moha/io/basis_database/cc-pvdz.nwchem
moha/io/basis_database/cc-pvqz.nwchem
moha/io/basis_database/cc-pvtz.nwchem
moha/io/basis_database/def2-qzvp.nwchem
moha/io/basis_database/def2-qzvpd.nwchem
moha/io/basis_database/def2-svpd.nwchem
moha/io/basis_database/def2-tzvp.nwchem
moha/io/basis_database/def2-tzvpd.nwchem
moha/io/basis_database/sto-3g.nwchem
moha/io/basis_database/sto-6g.nwchem
moha/io/test/__init__.py
moha/io/test/test_iogeometry.py
moha/posthf/__init__.py
moha/posthf/cc/__init__.py
moha/posthf/cc/auxiliary.py
moha/posthf/cc/ccsd.py
moha/posthf/cc/ccsd_t.py
moha/posthf/ci/__init__.py
moha/posthf/ci/ci_basis_set.py
moha/posthf/ci/ci_operator.py
moha/posthf/ci/ci_wavefunction.py
moha/posthf/ci/cis.py
moha/posthf/ci/cisd.py
moha/posthf/ci/fci.py
moha/posthf/ci/slater.py
moha-0.1.dist-info/AUTHORS
moha-0.1.dist-info/LICENSE
moha-0.1.dist-info/METADATA
moha-0.1.dist-info/WHEEL
moha-0.1.dist-info/top_level.txt
moha-0.1.dist-info/RECORD
