Metadata-Version: 2.1
Name: moha
Version: 0.1
Summary: A QM package
Home-page: https://zhaoyilin.github.io/moha/
Author: Yilin Zhao
Author-email: zhaoyilin1991@gmail.com
License: MIT
Platform: UNKNOWN
License-File: LICENSE
License-File: AUTHORS
